rst2h5p/__init__.py
rst2h5p/__main__.py
rst2h5p/directives.py
rst2h5p/elements.py
rst2h5p/main.py
rst2h5p/version.py
rst2h5p/writers/__init__.py
rst2h5p/writers/cp.py
rst2h5p/writers/visitor.py
rst2h5p-0.1.dist-info/METADATA
rst2h5p-0.1.dist-info/WHEEL
rst2h5p-0.1.dist-info/entry_points.txt
rst2h5p-0.1.dist-info/top_level.txt
rst2h5p-0.1.dist-info/RECORD
